{
  "type": "FeatureCollection",
  "features": [
    {
      "geometry": {
        "type": "Point",
        "coordinates": [
          7.178,
          9.18787
        ]
      },
      "type": "Feature",
      "properties": {
        "Name": "Abuja, Nigeria",
        "description": "",
        "icon": {
          "iconUrl": "http://f.cl.ly/items/3v1z1M0q3l1L3t0M041p/marker_white.png",
          "iconSize": [
            31,
            31
          ],
          "iconAnchor": [
            15,
            15
          ],
          "popupAnchor": [
            0,
            -21
          ],
          "className": "marker"
        }
      }
    }
  ]
}